cookiecutter_uv_example/__init__.py
cookiecutter_uv_example/foo.py
cookiecutter_uv_example-0.0.3.dist-info/LICENSE
cookiecutter_uv_example-0.0.3.dist-info/METADATA
cookiecutter_uv_example-0.0.3.dist-info/WHEEL
cookiecutter_uv_example-0.0.3.dist-info/top_level.txt
cookiecutter_uv_example-0.0.3.dist-info/RECORD
