Metadata-Version: 2.1
Name: cookiecutter-uv-example
Version: 0.0.3
Summary: This is a template repository for Python projects that use uv for their dependency management.
Author-email: Florian Maas <fpgmaas@gmail.com>
Project-URL: Homepage, https://fpgmaas.github.io/cookiecutter-uv-example/
Project-URL: Repository, https://github.com/fpgmaas/cookiecutter-uv-example
Project-URL: Documentation, https://fpgmaas.github.io/cookiecutter-uv-example/
Keywords: python
Requires-Python: <4.0,>=3.8
License-File: LICENSE
